LICENSE
MANIFEST.in
README.rst
setup.py
blog/__init__.py
blog/admin.py
blog/apps.py
blog/models.py
blog/urls.py
blog/views.py
blog/__pycache__/__init__.cpython-36.pyc
blog/__pycache__/admin.cpython-36.pyc
blog/__pycache__/apps.cpython-36.pyc
blog/__pycache__/models.cpython-36.pyc
blog/__pycache__/urls.cpython-36.pyc
blog/__pycache__/views.cpython-36.pyc
blog/api/__init__.py
blog/api/pagination.py
blog/api/serializers.py
blog/api/urls.py
blog/api/views.py
blog/api/__pycache__/__init__.cpython-36.pyc
blog/api/__pycache__/pagination.cpython-36.pyc
blog/api/__pycache__/ratelimitapicalls.cpython-36.pyc
blog/api/__pycache__/serializers.cpython-36.pyc
blog/api/__pycache__/urls.cpython-36.pyc
blog/api/__pycache__/views.cpython-36.pyc
blog/api/tests/test_apis.py
blog/api/tests/__pycache__/test_apis.cpython-27-PYTEST.pyc
blog/api/tests/__pycache__/test_apis.cpython-36-pytest-5.0.1.pyc
blog/migrations/0001_initial.py
blog/migrations/__init__.py
blog/migrations/__pycache__/0001_initial.cpython-36.pyc
blog/migrations/__pycache__/__init__.cpython-36.pyc
blog/tests/test_views.py
blog/tests/__pycache__/test_contact_views.cpython-36-pytest-5.0.1.pyc
blog/tests/__pycache__/test_views.cpython-36-pytest-5.0.1.pyc
blog_project/__init__.py
blog_project/celery.py
blog_project/settings.py
blog_project/urls.py
blog_project/wsgi.py
contact/__init__.py
contact/admin.py
contact/apps.py
contact/emails.py
contact/forms.py
contact/models.py
contact/tasks.py
contact/urls.py
contact/views.py
contact/__pycache__/__init__.cpython-36.pyc
contact/__pycache__/admin.cpython-36.pyc
contact/__pycache__/apps.cpython-36.pyc
contact/__pycache__/emails.cpython-36.pyc
contact/__pycache__/forms.cpython-36.pyc
contact/__pycache__/models.cpython-36.pyc
contact/__pycache__/tasks.cpython-36.pyc
contact/__pycache__/urls.cpython-36.pyc
contact/__pycache__/views.cpython-36.pyc
contact/migrations/__init__.py
contact/migrations/__pycache__/__init__.cpython-36.pyc
contact/tests/test_app.py
django_jo_blog_app.egg-info/PKG-INFO
django_jo_blog_app.egg-info/SOURCES.txt
django_jo_blog_app.egg-info/dependency_links.txt
django_jo_blog_app.egg-info/requires.txt
django_jo_blog_app.egg-info/top_level.txt
