Metadata-Version: 1.1
Name: django-jo-blog-app
Version: 0.1.3
Summary: blog app to nenable users to share posts
Home-page: https://www.example.com/
Author: Your Name
Author-email: john.maluki12@gmail.com
License: BSD License
Platform: UNKNOWN
Classifier: Environment :: Web Environment
Classifier: Framework :: Django :: 2.2
Classifier: License :: OSI Approved :: BSD License
Classifier: Programming Language :: Python :: 3.6
Classifier: Programming Language :: Python :: 3.7
